<?xml version="1.0" encoding="UTF-8"?><record_update table="sp_instance">
    <sp_instance action="DELETE">
        <active>true</active>
        <class_name/>
        <color>default</color>
        <css/>
        <glyph/>
        <id/>
        <order>1</order>
        <roles/>
        <short_description/>
        <size>md</size>
        <sp_column display_value="1">7a254e512fd510100056c886f699b60c</sp_column>
        <sp_widget display_value="SplitFriendsList">7d054a512fd510100056c886f699b646</sp_widget>
        <sys_class_name>sp_instance</sys_class_name>
        <sys_created_by>admin</sys_created_by>
        <sys_created_on>2020-06-08 17:22:26</sys_created_on>
        <sys_id>e03582912fd510100056c886f699b622</sys_id>
        <sys_mod_count>0</sys_mod_count>
        <sys_name/>
        <sys_package display_value="Split Bills" source="x_489137_split_bil">9a7fb19d2f9510100056c886f699b625</sys_package>
        <sys_policy/>
        <sys_scope display_value="Split Bills">9a7fb19d2f9510100056c886f699b625</sys_scope>
        <sys_update_name>sp_instance_e03582912fd510100056c886f699b622</sys_update_name>
        <sys_updated_by>admin</sys_updated_by>
        <sys_updated_on>2020-06-08 17:22:26</sys_updated_on>
        <title/>
        <url/>
        <widget_parameters/>
    </sp_instance>
    <sys_translated_text action="DELETE" query="documentkey=e03582912fd510100056c886f699b622"/>
    <sys_update_version action="INSERT_OR_UPDATE">
        <action>DELETE</action>
        <application display_value="Split Bills">9a7fb19d2f9510100056c886f699b625</application>
        <file_path/>
        <instance_id>ab4e3820dbf09cd89a4dcac5059619ee</instance_id>
        <instance_name>dev103178</instance_name>
        <name>sp_instance_e03582912fd510100056c886f699b622</name>
        <payload><![CDATA[<?xml version="1.0" encoding="UTF-8"?><record_update table="sp_instance"><sp_instance action="INSERT_OR_UPDATE"><active>true</active><class_name/><color>default</color><css/><glyph/><id/><order>1</order><roles/><short_description/><size>md</size><sp_column display_value="1">7a254e512fd510100056c886f699b60c</sp_column><sp_widget display_value="SplitFriendsList">7d054a512fd510100056c886f699b646</sp_widget><sys_class_name>sp_instance</sys_class_name><sys_created_by>admin</sys_created_by><sys_created_on>2020-06-08 17:22:26</sys_created_on><sys_id>e03582912fd510100056c886f699b622</sys_id><sys_mod_count>0</sys_mod_count><sys_name/><sys_package display_value="Split Bills" source="x_489137_split_bil">9a7fb19d2f9510100056c886f699b625</sys_package><sys_policy/><sys_scope display_value="Split Bills">9a7fb19d2f9510100056c886f699b625</sys_scope><sys_update_name>sp_instance_e03582912fd510100056c886f699b622</sys_update_name><sys_updated_by>admin</sys_updated_by><sys_updated_on>2020-06-08 17:22:26</sys_updated_on><title/><url/><widget_parameters/></sp_instance><sys_translated_text action="delete_multiple" query="documentkey=e03582912fd510100056c886f699b622"/></record_update>]]></payload>
        <payload_hash>1976068912</payload_hash>
        <record_name/>
        <reverted_from/>
        <source>2e7fb19d2f9510100056c886f699b627</source>
        <source_table>sys_update_set</source_table>
        <state>previous</state>
        <sys_created_by>admin</sys_created_by>
        <sys_created_on>2020-06-08 17:22:26</sys_created_on>
        <sys_id>a43582912fd510100056c886f699b624</sys_id>
        <sys_mod_count>0</sys_mod_count>
        <sys_recorded_at>17294f46f8e0000001</sys_recorded_at>
        <sys_updated_by>admin</sys_updated_by>
        <sys_updated_on>2020-06-08 17:22:26</sys_updated_on>
        <type>Instance</type>
        <update_guid>ec3582914cd51010d78942d68d5cb623</update_guid>
        <update_guid_history>ec3582914cd51010d78942d68d5cb623:1976068912</update_guid_history>
    </sys_update_version>
    <sys_metadata_delete action="INSERT_OR_UPDATE">
        <sys_audit_delete display_value="">872428ee2f5d10100056c886f699b6b7</sys_audit_delete>
        <sys_class_name>sys_metadata_delete</sys_class_name>
        <sys_created_by>admin</sys_created_by>
        <sys_created_on>2020-06-12 07:30:57</sys_created_on>
        <sys_db_object display_value="" name="sp_instance">sp_instance</sys_db_object>
        <sys_id>05020bd1394348f285b7699e1bc75bc1</sys_id>
        <sys_metadata>e03582912fd510100056c886f699b622</sys_metadata>
        <sys_mod_count>0</sys_mod_count>
        <sys_name/>
        <sys_package display_value="Split Bills" source="x_489137_split_bil">9a7fb19d2f9510100056c886f699b625</sys_package>
        <sys_parent/>
        <sys_policy/>
        <sys_scope display_value="Split Bills">9a7fb19d2f9510100056c886f699b625</sys_scope>
        <sys_scope_delete display_value="">2a3dc67cdf104d5a8865d88a74da40c1</sys_scope_delete>
        <sys_update_name>sp_instance_e03582912fd510100056c886f699b622</sys_update_name>
        <sys_update_version display_value="sp_instance_e03582912fd510100056c886f699b622">a43582912fd510100056c886f699b624</sys_update_version>
        <sys_updated_by>admin</sys_updated_by>
        <sys_updated_on>2020-06-12 07:30:57</sys_updated_on>
    </sys_metadata_delete>
</record_update>
